{
  "versions": {
    "0.1.0": {
      "version": "0.1.0", 
      "opam": {
        "url": "http://zoggy.github.com/ocf/ocf-0.1.0.tar.gz", 
        "checksum": "51e10c39063df2257f1b32fe699f72b3", 
        "files": []
      }, 
      "esy": {
        "buildsInSource": true, 
        "build": [
          "./configure --prefix $cur__install", 
          "make all", 
          "make install", 
          "(opam-installer --prefix=$cur__install || true)"
        ], 
        "exportedEnv": {
          "ocf_version": {
            "scope": "global", 
            "val": "0.1.0"
          }, 
          "ocf_enable": {
            "scope": "global", 
            "val": "enable"
          }, 
          "ocf_installed": {
            "scope": "global", 
            "val": "true"
          }
        }
      }, 
      "dependencies": {
        "@opam-alpha/camlp4": "*", 
        "@opam-alpha/yojson": ">= 1.1.8", 
        "@opam-alpha/ocamlfind": "*", 
        "substs": "esy-ocaml/substs", 
        "@opam-alpha/ppx_tools": ">= 0.99.0", 
        "opam-installer-bin": "esy-ocaml/opam-installer-bin"
      }, 
      "scripts": {}, 
      "peerDependencies": {
        "ocaml": ">= 4.02.1 < 4.03.0"
      }, 
      "name": "@opam-alpha/ocf"
    }, 
    "0.4.0": {
      "version": "0.4.0", 
      "opam": {
        "url": "http://zoggy.github.com/ocf/ocf-0.4.0.tar.gz", 
        "checksum": "e3ca7aae3bda436711ad6c0719ecfbf9", 
        "files": []
      }, 
      "esy": {
        "buildsInSource": true, 
        "build": [
          "./configure --prefix $cur__install", 
          "make all", 
          "make install", 
          "(opam-installer --prefix=$cur__install || true)"
        ], 
        "exportedEnv": {
          "ocf_version": {
            "scope": "global", 
            "val": "0.4.0"
          }, 
          "ocf_enable": {
            "scope": "global", 
            "val": "enable"
          }, 
          "ocf_installed": {
            "scope": "global", 
            "val": "true"
          }
        }
      }, 
      "dependencies": {
        "substs": "esy-ocaml/substs", 
        "@opam-alpha/ocamlfind": "*", 
        "@opam-alpha/yojson": ">= 1.1.8", 
        "opam-installer-bin": "esy-ocaml/opam-installer-bin", 
        "@opam-alpha/ppx_tools": ">= 0.99.0"
      }, 
      "scripts": {}, 
      "peerDependencies": {
        "ocaml": ">= 4.02.1 < 4.03.0"
      }, 
      "name": "@opam-alpha/ocf"
    }, 
    "0.3.0": {
      "version": "0.3.0", 
      "opam": {
        "url": "http://zoggy.github.com/ocf/ocf-0.3.0.tar.gz", 
        "checksum": "2cc3dfd3d4f2c0caf6a7978bf19b5dff", 
        "files": []
      }, 
      "esy": {
        "buildsInSource": true, 
        "build": [
          "./configure --prefix $cur__install", 
          "make all", 
          "make install", 
          "(opam-installer --prefix=$cur__install || true)"
        ], 
        "exportedEnv": {
          "ocf_version": {
            "scope": "global", 
            "val": "0.3.0"
          }, 
          "ocf_enable": {
            "scope": "global", 
            "val": "enable"
          }, 
          "ocf_installed": {
            "scope": "global", 
            "val": "true"
          }
        }
      }, 
      "dependencies": {
        "@opam-alpha/camlp4": "*", 
        "@opam-alpha/yojson": ">= 1.1.8", 
        "@opam-alpha/ocamlfind": "*", 
        "substs": "esy-ocaml/substs", 
        "@opam-alpha/ppx_tools": ">= 0.99.0", 
        "opam-installer-bin": "esy-ocaml/opam-installer-bin"
      }, 
      "scripts": {}, 
      "peerDependencies": {
        "ocaml": ">= 4.02.1 < 4.03.0"
      }, 
      "name": "@opam-alpha/ocf"
    }, 
    "0.5.0": {
      "version": "0.5.0", 
      "opam": {
        "url": "https://github.com/zoggy/ocf/archive/release-0.5.0.tar.gz", 
        "checksum": "e4e73bea9472b2e77f62604033b098d8", 
        "files": []
      }, 
      "esy": {
        "buildsInSource": true, 
        "build": [
          "./configure --prefix $cur__install", 
          "make all", 
          "make install", 
          "(opam-installer --prefix=$cur__install || true)"
        ], 
        "exportedEnv": {
          "ocf_version": {
            "scope": "global", 
            "val": "0.5.0"
          }, 
          "ocf_enable": {
            "scope": "global", 
            "val": "enable"
          }, 
          "ocf_installed": {
            "scope": "global", 
            "val": "true"
          }
        }
      }, 
      "dependencies": {
        "substs": "esy-ocaml/substs", 
        "@opam-alpha/ocamlfind": "*", 
        "@opam-alpha/yojson": ">= 1.3.2", 
        "opam-installer-bin": "esy-ocaml/opam-installer-bin", 
        "@opam-alpha/ppx_tools": ">= 4.03.0"
      }, 
      "scripts": {}, 
      "peerDependencies": {
        "ocaml": ">= 4.03.0"
      }, 
      "name": "@opam-alpha/ocf"
    }, 
    "0.2.0": {
      "version": "0.2.0", 
      "opam": {
        "url": "http://zoggy.github.com/ocf/ocf-0.2.0.tar.gz", 
        "checksum": "93844cbc997014ed0ac03d78c36cd7e4", 
        "files": []
      }, 
      "esy": {
        "buildsInSource": true, 
        "build": [
          "./configure --prefix $cur__install", 
          "make all", 
          "make install", 
          "(opam-installer --prefix=$cur__install || true)"
        ], 
        "exportedEnv": {
          "ocf_version": {
            "scope": "global", 
            "val": "0.2.0"
          }, 
          "ocf_enable": {
            "scope": "global", 
            "val": "enable"
          }, 
          "ocf_installed": {
            "scope": "global", 
            "val": "true"
          }
        }
      }, 
      "dependencies": {
        "@opam-alpha/camlp4": "*", 
        "@opam-alpha/yojson": ">= 1.1.8", 
        "@opam-alpha/ocamlfind": "*", 
        "substs": "esy-ocaml/substs", 
        "@opam-alpha/ppx_tools": ">= 0.99.0", 
        "opam-installer-bin": "esy-ocaml/opam-installer-bin"
      }, 
      "scripts": {}, 
      "peerDependencies": {
        "ocaml": ">= 4.02.1 < 4.03.0"
      }, 
      "name": "@opam-alpha/ocf"
    }
  }
}