{
  "versions": {
    "0.3.0": {
      "version": "0.3.0", 
      "opam": {
        "url": "https://github.com/dsheets/ocaml-sodium/archive/0.3.0.tar.gz", 
        "checksum": "7dafca32822d88e229648cec369bcc7e", 
        "files": []
      }, 
      "esy": {
        "buildsInSource": true, 
        "build": [
          "make", 
          "env IS_FREEBSD=true make", 
          "make PREFIX=$cur__install install", 
          "(opam-installer --prefix=$cur__install || true)"
        ], 
        "exportedEnv": {
          "sodium_installed": {
            "scope": "global", 
            "val": "true"
          }, 
          "sodium_enable": {
            "scope": "global", 
            "val": "enable"
          }, 
          "sodium_version": {
            "scope": "global", 
            "val": "0.3.0"
          }
        }
      }, 
      "dependencies": {
        "substs": "esy-ocaml/substs", 
        "@opam-alpha/ocamlfind": "*", 
        "opam-installer-bin": "esy-ocaml/opam-installer-bin", 
        "@opam-alpha/ctypes": ">= 0.3.2 < 0.4.0"
      }, 
      "scripts": {}, 
      "peerDependencies": {
        "ocaml": ">= 4.01.0"
      }, 
      "name": "@opam-alpha/sodium"
    }, 
    "0.4.1": {
      "version": "0.4.1", 
      "opam": {
        "url": "https://github.com/dsheets/ocaml-sodium/archive/0.4.1.tar.gz", 
        "checksum": "04ab169db9f477d1da50dc97211027e8", 
        "files": []
      }, 
      "esy": {
        "buildsInSource": true, 
        "build": [
          "make", 
          "make CFLAGS=-I/usr/local/include -L/usr/local/lib", 
          "make PREFIX=$cur__install install", 
          "(opam-installer --prefix=$cur__install || true)"
        ], 
        "exportedEnv": {
          "sodium_installed": {
            "scope": "global", 
            "val": "true"
          }, 
          "sodium_enable": {
            "scope": "global", 
            "val": "enable"
          }, 
          "sodium_version": {
            "scope": "global", 
            "val": "0.4.1"
          }
        }
      }, 
      "dependencies": {
        "substs": "esy-ocaml/substs", 
        "@opam-alpha/ocamlfind": "*", 
        "opam-installer-bin": "esy-ocaml/opam-installer-bin", 
        "@opam-alpha/ctypes": ">= 0.4.0 < 0.6.0"
      }, 
      "scripts": {}, 
      "peerDependencies": {
        "ocaml": ">= 4.01.0"
      }, 
      "name": "@opam-alpha/sodium"
    }, 
    "0.2.1": {
      "version": "0.2.1", 
      "opam": {
        "url": "https://github.com/dsheets/ocaml-sodium/archive/0.2.1.tar.gz", 
        "checksum": "a197001f4c3ebe8c6a43eec4a4957c1e", 
        "files": []
      }, 
      "esy": {
        "buildsInSource": true, 
        "build": [
          "make", 
          "make PREFIX=$cur__install install", 
          "(opam-installer --prefix=$cur__install || true)"
        ], 
        "exportedEnv": {
          "sodium_installed": {
            "scope": "global", 
            "val": "true"
          }, 
          "sodium_enable": {
            "scope": "global", 
            "val": "enable"
          }, 
          "sodium_version": {
            "scope": "global", 
            "val": "0.2.1"
          }
        }
      }, 
      "dependencies": {
        "substs": "esy-ocaml/substs", 
        "@opam-alpha/ocamlfind": "*", 
        "@opam-alpha/ctypes-foreign": "*", 
        "opam-installer-bin": "esy-ocaml/opam-installer-bin", 
        "@opam-alpha/ctypes": ">= 0.3.2"
      }, 
      "scripts": {}, 
      "peerDependencies": {
        "ocaml": ">= 4.2.3"
      }, 
      "name": "@opam-alpha/sodium"
    }, 
    "0.2.0": {
      "version": "0.2.0", 
      "opam": {
        "url": "https://github.com/dsheets/ocaml-sodium/archive/0.2.0.tar.gz", 
        "checksum": "081e374e4d43a88e35c58151cd45e0dd", 
        "files": []
      }, 
      "esy": {
        "buildsInSource": true, 
        "build": [
          "make", 
          "make PREFIX=$cur__install install", 
          "(opam-installer --prefix=$cur__install || true)"
        ], 
        "exportedEnv": {
          "sodium_installed": {
            "scope": "global", 
            "val": "true"
          }, 
          "sodium_enable": {
            "scope": "global", 
            "val": "enable"
          }, 
          "sodium_version": {
            "scope": "global", 
            "val": "0.2.0"
          }
        }
      }, 
      "dependencies": {
        "substs": "esy-ocaml/substs", 
        "@opam-alpha/ocamlfind": "*", 
        "@opam-alpha/ctypes-foreign": "*", 
        "opam-installer-bin": "esy-ocaml/opam-installer-bin", 
        "@opam-alpha/ctypes": ">= 0.3.0"
      }, 
      "scripts": {}, 
      "peerDependencies": {
        "ocaml": ">= 4.2.3"
      }, 
      "name": "@opam-alpha/sodium"
    }, 
    "0.1.0": {
      "version": "0.1.0", 
      "opam": {
        "url": "https://github.com/dsheets/ocaml-sodium/archive/0.1.0.tar.gz", 
        "checksum": "2e22bd3b3941fa2bb2152ad98d74025d", 
        "files": []
      }, 
      "esy": {
        "buildsInSource": true, 
        "build": [
          "make", 
          "make PREFIX=$cur__install install", 
          "(opam-installer --prefix=$cur__install || true)"
        ], 
        "exportedEnv": {
          "sodium_installed": {
            "scope": "global", 
            "val": "true"
          }, 
          "sodium_enable": {
            "scope": "global", 
            "val": "enable"
          }, 
          "sodium_version": {
            "scope": "global", 
            "val": "0.1.0"
          }
        }
      }, 
      "dependencies": {
        "substs": "esy-ocaml/substs", 
        "@opam-alpha/ocamlfind": "*", 
        "opam-installer-bin": "esy-ocaml/opam-installer-bin", 
        "@opam-alpha/ctypes": ">= 0.1.1 < 0.3.0"
      }, 
      "scripts": {}, 
      "peerDependencies": {
        "ocaml": ">= 4.2.3"
      }, 
      "name": "@opam-alpha/sodium"
    }, 
    "0.5.0": {
      "version": "0.5.0", 
      "opam": {
        "url": "https://github.com/dsheets/ocaml-sodium/archive/0.5.0.tar.gz", 
        "checksum": "07c585883270fe5d1eee84d94f26864a", 
        "files": []
      }, 
      "esy": {
        "buildsInSource": true, 
        "build": [
          "make", 
          "make CFLAGS=-I/usr/local/include -L/usr/local/lib", 
          "make PREFIX=$cur__install install", 
          "(opam-installer --prefix=$cur__install || true)"
        ], 
        "exportedEnv": {
          "sodium_installed": {
            "scope": "global", 
            "val": "true"
          }, 
          "sodium_enable": {
            "scope": "global", 
            "val": "enable"
          }, 
          "sodium_version": {
            "scope": "global", 
            "val": "0.5.0"
          }
        }
      }, 
      "dependencies": {
        "substs": "esy-ocaml/substs", 
        "@opam-alpha/ocamlfind": "*", 
        "opam-installer-bin": "esy-ocaml/opam-installer-bin", 
        "@opam-alpha/ctypes": ">= 0.4.0 < 0.6.0"
      }, 
      "scripts": {}, 
      "peerDependencies": {
        "ocaml": ">= 4.01.0"
      }, 
      "name": "@opam-alpha/sodium"
    }
  }
}