{
  "versions": {
    "1.0.0": {
      "version": "1.0.0", 
      "opam": {
        "url": "http://forge.ocamlcore.org/frs/download.php/1005/ocaml-srs-1.0.0.tar.gz", 
        "checksum": "b5522b6ca3488fb31ef2421757d96389", 
        "files": []
      }, 
      "esy": {
        "buildsInSource": true, 
        "build": [
          "ocaml setup.ml -configure --prefix $cur__install", 
          "ocaml setup.ml -build", 
          "ocaml setup.ml -install", 
          "(opam-installer --prefix=$cur__install || true)"
        ], 
        "exportedEnv": {
          "srs_installed": {
            "scope": "global", 
            "val": "true"
          }, 
          "srs_version": {
            "scope": "global", 
            "val": "1.0.0"
          }, 
          "srs_enable": {
            "scope": "global", 
            "val": "enable"
          }
        }
      }, 
      "dependencies": {
        "substs": "esy-ocaml/substs", 
        "@opam-alpha/ocamlfind": "*", 
        "opam-installer-bin": "esy-ocaml/opam-installer-bin"
      }, 
      "scripts": {}, 
      "peerDependencies": {
        "ocaml": ">= 4.2.3"
      }, 
      "name": "@opam-alpha/srs"
    }
  }
}